{
  "content": [
    {
      "content": null,
      "created": "2022-03-01T09:47:13.900299Z",
      "format": null,
      "last_modified": "2022-03-01T09:46:37.842175Z",
      "mimetype": null,
      "name": "python.ipynb",
      "path": "python.ipynb",
      "size": 12962,
      "type": "notebook",
      "writable": true
    },
    {
      "content": null,
      "created": "2022-03-01T09:47:13.900299Z",
      "format": null,
      "last_modified": "2022-03-01T09:47:12.416206Z",
      "mimetype": "text/markdown",
      "name": "README.md",
      "path": "README.md",
      "size": 2141,
      "type": "file",
      "writable": true
    }
  ],
  "created": "2022-03-01T09:47:13.900299Z",
  "format": "json",
  "last_modified": "2022-03-01T09:47:13.900299Z",
  "mimetype": null,
  "name": "",
  "path": "",
  "size": null,
  "type": "directory",
  "writable": true
}